Metadata-Version: 2.1
Name: read_text_from_image_sabrinabm94
Version: 0.0.2
Summary: Package to extract text from images using Python
Home-page: https://github.com/sabrinabm94/python/tree/master/data-engineering/challenges/package
Author: Sabrina B. M.
Author-email: "Sabrina B. M." <sabrinabm94@gmail.com>
License: MIT License
Project-URL: Homepage, https://github.com/sabrinabm94/python/tree/master/data-engineering/challenges/package
Project-URL: Issues, https://github.com/sabrinabm94/python/tree/master/data-engineering/challenges/package/issues
Classifier: Programming Language :: Python :: 3
Classifier: Programming Language :: Python :: 3.8
Classifier: License :: OSI Approved :: MIT License
Classifier: Operating System :: OS Independent
Requires-Python: >=3.8
Requires-Dist: pillow
Requires-Dist: pytesseract
